parabar/__init__.py
parabar/parabar.py
parabar-0.3.0.dist-info/LICENSE
parabar-0.3.0.dist-info/METADATA
parabar-0.3.0.dist-info/WHEEL
parabar-0.3.0.dist-info/top_level.txt
parabar-0.3.0.dist-info/RECORD
