Metadata-Version: 2.1
Name: parabar
Version: 0.3.0
Summary: Python multiprocessing with progress bars
Author-email: Matthew Mould <mattdmould@gmail.com>
Project-URL: Homepage, https://github.com/mdmould/parabar
Classifier: Programming Language :: Python :: 3
Classifier: License :: OSI Approved :: MIT License
Classifier: Operating System :: OS Independent
Requires-Python: >=3.9
License-File: LICENSE
Requires-Dist: tqdm
Requires-Dist: pathos
